MANIFEST.in
README.md
VEDIS_LICENSE
setup.py
ctypesgen/__init__.py
ctypesgen/ctypesgen.py
ctypesgen/ctypesgencore/__init__.py
ctypesgen/ctypesgencore/ctypedescs.py
ctypesgen/ctypesgencore/descriptions.py
ctypesgen/ctypesgencore/expressions.py
ctypesgen/ctypesgencore/libraryloader.py
ctypesgen/ctypesgencore/messages.py
ctypesgen/ctypesgencore/old libraryloader.py
ctypesgen/ctypesgencore/options.py
ctypesgen/ctypesgencore/parser/__init__.py
ctypesgen/ctypesgencore/parser/cdeclarations.py
ctypesgen/ctypesgencore/parser/cgrammar.py
ctypesgen/ctypesgencore/parser/cparser.py
ctypesgen/ctypesgencore/parser/ctypesparser.py
ctypesgen/ctypesgencore/parser/datacollectingparser.py
ctypesgen/ctypesgencore/parser/lex.py
ctypesgen/ctypesgencore/parser/lextab.py
ctypesgen/ctypesgencore/parser/parsetab.py
ctypesgen/ctypesgencore/parser/pplexer.py
ctypesgen/ctypesgencore/parser/preprocessor.py
ctypesgen/ctypesgencore/parser/yacc.py
ctypesgen/ctypesgencore/printer/__init__.py
ctypesgen/ctypesgencore/printer/defaultheader.py
ctypesgen/ctypesgencore/printer/preamble.py
ctypesgen/ctypesgencore/printer/printer.py
ctypesgen/ctypesgencore/printer/test.py
ctypesgen/ctypesgencore/processor/__init__.py
ctypesgen/ctypesgencore/processor/dependencies.py
ctypesgen/ctypesgencore/processor/operations.py
ctypesgen/ctypesgencore/processor/pipeline.py
docs/Makefile
docs/api.rst
docs/conf.py
docs/custom_commands.rst
docs/index.rst
docs/installation.rst
docs/quickstart.rst
vedis/__init__.py
vedis/core.py
vedis/tests.py
vedis.egg-info/PKG-INFO
vedis.egg-info/SOURCES.txt
vedis.egg-info/dependency_links.txt
vedis.egg-info/not-zip-safe
vedis.egg-info/top_level.txt
vedis/src/vedis.c
vedis/src/vedis.h