Metadata-Version: 1.0
Name: vedis
Version: 0.1.7
Summary: Python bindings for Vedis, the embedded NoSQL database.
Home-page: UNKNOWN
Author: Charles Leifer
Author-email: UNKNOWN
License: UNKNOWN
Platform: UNKNOWN
